drlenvs/__init__.py
drlenvs/kuka_visual_reach.py
drlenvs-0.0.1.dist-info/LICENSE
drlenvs-0.0.1.dist-info/METADATA
drlenvs-0.0.1.dist-info/WHEEL
drlenvs-0.0.1.dist-info/top_level.txt
drlenvs-0.0.1.dist-info/RECORD
